djangorestframework_camel_case2/__init__.py
djangorestframework_camel_case2/parser.py
djangorestframework_camel_case2/render.py
djangorestframework_camel_case2/settings.py
djangorestframework_camel_case2/util.py
djangorestframework_camel_case2-0.3.0.dist-info/LICENSE
djangorestframework_camel_case2-0.3.0.dist-info/WHEEL
djangorestframework_camel_case2-0.3.0.dist-info/METADATA
djangorestframework_camel_case2-0.3.0.dist-info/RECORD
