Metadata-Version: 2.1
Name: djangorestframework-camel-case2
Version: 0.3.0
Summary: Camel case JSON support for Django REST framework
Home-page: https://github.com/jozo/djangorestframework-camel-case2
Keywords: django,camel-case,django-rest-framework
Author: jozo
Author-email: hi@jozo.io
Requires-Python: >=3.5,<4.0
Classifier: Programming Language :: Python :: 3
Classifier: Programming Language :: Python :: 3.5
Classifier: Programming Language :: Python :: 3.6
Classifier: Programming Language :: Python :: 3.7
Classifier: Programming Language :: Python :: 3.8
Requires-Dist: django (>=2.2)
Requires-Dist: djangorestframework (>=3.9)
Project-URL: Repository, https://github.com/jozo/djangorestframework-camel-case2
